ptcrossd/__init__.py
ptcrossd/_version.py
ptcrossd/ptcrossd.py
ptcrossd-1.0.6.dist-info/licenses/LICENSE
ptcrossd-1.0.6.dist-info/METADATA
ptcrossd-1.0.6.dist-info/WHEEL
ptcrossd-1.0.6.dist-info/entry_points.txt
ptcrossd-1.0.6.dist-info/top_level.txt
ptcrossd-1.0.6.dist-info/RECORD
